modularRobotics/__init__.py
modularRobotics/test.py
modularRobotics-0.1.9.1.dist-info/LICENSE
modularRobotics-0.1.9.1.dist-info/METADATA
modularRobotics-0.1.9.1.dist-info/WHEEL
modularRobotics-0.1.9.1.dist-info/top_level.txt
modularRobotics-0.1.9.1.dist-info/RECORD
