Metadata-Version: 2.1
Name: modularRobotics
Version: 0.1.9.1
Summary: A package to controll products of Modular robotics
Home-page: https://github.com/Fischchen/modular-robotics
Author: Fischchen
Author-email: tipp.klever@gmail.com
License: MIT
Download-URL: https://github.com/Fischchen/modular-robotics/archive/v0.1-alpha.tar.gz
Keywords: SOME,MEANINGFULL,KEYWORDS
Platform: UNKNOWN
Classifier: Development Status :: 3 - Alpha
Classifier: Intended Audience :: Developers
Classifier: Topic :: Software Development :: Build Tools
Classifier: License :: OSI Approved :: MIT License
Classifier: Programming Language :: Python :: 3
Classifier: Programming Language :: Python :: 3.4
Classifier: Programming Language :: Python :: 3.5
Classifier: Programming Language :: Python :: 3.6
Requires-Dist: validators
Requires-Dist: beautifulsoup4
